kgpr_core/__init__.py
kgpr_core/py.typed
kgpr_core/amazon/__init__.py
kgpr_core/amazon/py.typed
kgpr_core/amazon/eks/__init__.py
kgpr_core/amazon/eks/kresource.py
kgpr_core/amazon/eks/provider.py
kgpr_core/amazon/eks/py.typed
kgpr_core/digitalocean/__init__.py
kgpr_core/digitalocean/py.typed
kgpr_core/digitalocean/kubernetes/__init__.py
kgpr_core/digitalocean/kubernetes/kresource.py
kgpr_core/digitalocean/kubernetes/provider.py
kgpr_core/digitalocean/kubernetes/py.typed
kgpr_core/google/__init__.py
kgpr_core/google/py.typed
kgpr_core/google/gke/__init__.py
kgpr_core/google/gke/kresource.py
kgpr_core/google/gke/provider.py
kgpr_core/google/gke/py.typed
kgpr_core/k3d/__init__.py
kgpr_core/k3d/py.typed
kgpr_core/k3d/generic/__init__.py
kgpr_core/k3d/generic/provider.py
kgpr_core/k3d/generic/py.typed
kgpr_core/kind/__init__.py
kgpr_core/kind/py.typed
kgpr_core/kind/generic/__init__.py
kgpr_core/kind/generic/provider.py
kgpr_core/kind/generic/py.typed
kgpr_core-0.8.3.dist-info/METADATA
kgpr_core-0.8.3.dist-info/WHEEL
kgpr_core-0.8.3.dist-info/top_level.txt
kgpr_core-0.8.3.dist-info/RECORD
