Metadata-Version: 2.1
Name: kgpr-core
Version: 0.8.3
Summary: KubraGen Providers: Core
Home-page: https://github.com/RangelReale/kgpr_core
Author: Rangel Reale
Author-email: rangelreale@gmail.com
License: UNKNOWN
Platform: UNKNOWN
Classifier: Programming Language :: Python :: 3
Classifier: License :: OSI Approved :: MIT License
Classifier: Operating System :: OS Independent
Requires-Python: >=3.6
Requires-Dist: kubragen (>=0.8.2)
